{
  "type": "FeatureCollection",
  "features": [
    {
      "type": "Feature",
      "geometry": {
        "coordinates": [
          12.922648,
          50.836097
        ],
        "type": "Point"
      },
      "properties": {
        "name": "Marx-O-Maly is calling you to Chemnitz ",
        "description": "https://bannergress.com/banner/marx-o-maly-is-calling-you-to-chemnitz-2fc4"
      },
      "id": "U2MDE"
    }
  ]
}
