{
  "type": "FeatureCollection",
  "features": [
    {
      "type": "Feature",
      "geometry": {
        "coordinates": [
          12.923279,
          50.835871
        ],
        "type": "Point"
      },
      "properties": {
        "name": "Marx-O-Maly is calling you to Chemnitz "
      },
      "id": "U2MDE"
    }
  ]
}