{
    "type": "FeatureCollection",
    "features": [
        {
            "type": "Feature",
            "geometry": {
                "coordinates": [
                    3.618994,
                    51.495449
                ],
                "type": "Point"
            },
            "properties": {
                "name": "Chemnitz  +Theta - Middelburg",
                "url": "https://bannergress.com/banner/chemnitz-theta-middelburg-6751",
                "picture": "https://api.bannergress.com/bnrs/pictures/735ff0ce57508a05a00c911759361cd6"
            },
            "id": "6751"
        },
        {
            "type": "Feature",
            "geometry": {
                "coordinates": [
                    12.9224599,
                    50.8359178
                ],
                "type": "Point"
            },
            "properties": {
                "name": "Marx-O-Maly is calling you to Chemnitz!",
                "url": "https://bannergress.com/banner/marx-o-maly-is-calling-you-to-chemnitz-2fc4",
                "picture": "https://api.bannergress.com/bnrs/pictures/9f3c3d11f740189d41af5f1d38fd7d18"
            },
            "id": "2fc4"
        }
    ]
}
