{
  "type": "FeatureCollection",
  "features": [
    {
      "type": "Feature",
      "geometry": {
        "coordinates": [
          13.41451,
          52.521764
        ],
        "type": "Point"
      },
      "properties": {
        "name": "Marx is calling you - Berlin",
        "description": "https://bannergress.com/banner/marx-is-calling-you-berlin-6c02"
      },
      "id": "cxNDk"
    },
    {
      "type": "Feature",
      "geometry": {
        "coordinates": [
          13.261756,
          53.561402
        ],
        "type": "Point"
      },
      "properties": {
        "name": "Marx is calling you - Neubrandenburg ",
        "description": "https://bannergress.com/banner/marx-is-calling-you-neubrandenburg-459a"
      },
      "id": "kxMzQ"
    },
    {
      "type": "Feature",
      "geometry": {
        "coordinates": [
          12.923279,
          50.835871
        ],
        "type": "Point"
      },
      "properties": {
        "name": "Marx is calling you to Chemnitz",
        "description": "https://bannergress.com/banner/marx-is-calling-you-to-chemnitz-0dd8"
      },
      "id": "U2MDE"
    }
  ]
}
